nginx_updater/__init__.py
nginx_updater/logger.py
nginx_updater/py.typed
nginx_updater/types.py
nginx_updater/updater.py
nginx_updater/utils.py
nginx_updater-1.0.5.dist-info/LICENSE
nginx_updater-1.0.5.dist-info/METADATA
nginx_updater-1.0.5.dist-info/WHEEL
nginx_updater-1.0.5.dist-info/top_level.txt
nginx_updater-1.0.5.dist-info/RECORD
