Metadata-Version: 2.1
Name: nginx-updater
Version: 1.0.5
Summary: Python module updater that uses nginx as backend
Home-page: https://github.com/pradishb/nginx-updater
Author: Pradish Bijukchhe
Author-email: pradishbijukchhe@gmail.com
Project-URL: Bug Tracker, https://github.com/pradishb/nginx-updater/issues
Classifier: Programming Language :: Python :: 3
Classifier: License :: OSI Approved :: MIT License
Requires-Python: >=3
License-File: LICENSE
Requires-Dist: requests
